e3md/__init__.py
e3md/_kan.py
e3md/config.py
e3md/data.py
e3md/keys.py
e3md/main.py
e3md/metrics.py
e3md/n2p2.py
e3md/potentials.py
e3md/stats.py
e3md/train.py
e3md-0.1.0.dist-info/entry_points.txt
e3md-0.1.0.dist-info/LICENSE.txt
e3md-0.1.0.dist-info/WHEEL
e3md-0.1.0.dist-info/METADATA
e3md-0.1.0.dist-info/RECORD
