Metadata-Version: 2.1
Name: e3md
Version: 0.1.0
Summary: Library for machine learning on physical tensors
Keywords: machine learning,e3nn-jax,physics
Author-email: Martin Uhrin <martin.uhrin.10@ucl.ac.uk>
Requires-Python: >=3.8
Classifier: Development Status :: 4 - Beta
Classifier: License :: OSI Approved :: GNU Lesser General Public License v3 or later (LGPLv3+)
Classifier: Programming Language :: Python
Classifier: Programming Language :: Python :: 3.8
Classifier: Programming Language :: Python :: 3.9
Classifier: Programming Language :: Python :: 3.10
Classifier: Programming Language :: Python :: 3.11
Classifier: Programming Language :: Python :: 3.12
Requires-Dist: ase
Requires-Dist: hydra-core
Requires-Dist: jax
Requires-Dist: jaxlib
Requires-Dist: jraph
Requires-Dist: orbax-checkpoint
Requires-Dist: e3nn-jax
Requires-Dist: equinox
Requires-Dist: tensorial
Requires-Dist: flit ; extra == "dev"
Requires-Dist: ipython ; extra == "dev"
Requires-Dist: pytest ; extra == "dev"
Requires-Dist: pytest-cov ; extra == "dev"
Requires-Dist: pre-commit ; extra == "dev"
Requires-Dist: pylint ; extra == "dev"
Requires-Dist: black ; extra == "dev"
Requires-Dist: docutils ; extra == "docs"
Requires-Dist: jupyter ; extra == "docs"
Requires-Dist: nbsphinx ; extra == "docs"
Requires-Dist: pandoc ; extra == "docs"
Requires-Dist: sphinx ; extra == "docs"
Requires-Dist: sphinx-autobuild ; extra == "docs"
Project-URL: Home, https://github.com/muhrin/e3md
Project-URL: Source, https://github.com/muhrin/e3md
Provides-Extra: dev
Provides-Extra: docs
